CommentGPT/__init__.py
CommentGPT/__main__.py
CommentGPT/chatgpt_interface_wrapper.py
CommentGPT/commenter.py
CommentGPT/filter.py
CommentGPT/main.py
CommentGPT-0.2.dist-info/METADATA
CommentGPT-0.2.dist-info/WHEEL
CommentGPT-0.2.dist-info/top_level.txt
CommentGPT-0.2.dist-info/RECORD
